markwise
